ammcpc/__init__.py
ammcpc/__main__.py
ammcpc/ammcpc.py
ammcpc-0.3.0.dist-info/LICENSE
ammcpc-0.3.0.dist-info/METADATA
ammcpc-0.3.0.dist-info/WHEEL
ammcpc-0.3.0.dist-info/entry_points.txt
ammcpc-0.3.0.dist-info/top_level.txt
ammcpc-0.3.0.dist-info/RECORD
